pat2vec/__init__.py
pat2vec/main_pat2vec.py
pat2vec/pat2vec_get_methods/__init__.py
pat2vec/pat2vec_get_methods/get_method_appointments.py
pat2vec/pat2vec_get_methods/get_method_bed.py
pat2vec/pat2vec_get_methods/get_method_bloods.py
pat2vec/pat2vec_get_methods/get_method_bmi.py
pat2vec/pat2vec_get_methods/get_method_core02.py
pat2vec/pat2vec_get_methods/get_method_core_resus.py
pat2vec/pat2vec_get_methods/get_method_current_pat_annotations_mrc_cs.py
pat2vec/pat2vec_get_methods/get_method_demo.py
pat2vec/pat2vec_get_methods/get_method_demographics.py
pat2vec/pat2vec_get_methods/get_method_diagnostics.py
pat2vec/pat2vec_get_methods/get_method_drugs.py
pat2vec/pat2vec_get_methods/get_method_hosp_site.py
pat2vec/pat2vec_get_methods/get_method_news.py
pat2vec/pat2vec_get_methods/get_method_pat_annotations.py
pat2vec/pat2vec_get_methods/get_method_report_annotations.py
pat2vec/pat2vec_get_methods/get_method_smoking.py
pat2vec/pat2vec_get_methods/get_method_textual_obs_annotations.py
pat2vec/pat2vec_get_methods/get_method_vte_status.py
pat2vec/pat2vec_main_methods/__init__.py
pat2vec/pat2vec_main_methods/main_batch.py
pat2vec/pat2vec_pat_list/__init__.py
pat2vec/pat2vec_pat_list/get_patient_treatment_list.py
pat2vec/pat2vec_search/cogstack_search_methods.py
pat2vec/pat2vec_search/data_helper_functions.py
pat2vec/pat2vec_search/matcher.py
pat2vec/pat2vec_search/nearest.py
pat2vec/pat2vec_search/search_helper_functions.py
pat2vec/pat2vec_search/search_multiprocess.py
pat2vec/patvec_get_batch_methods/__init__.py
pat2vec/patvec_get_batch_methods/get_merged_batches.py
pat2vec/patvec_get_batch_methods/get_prefetch_batches.py
pat2vec/patvec_get_batch_methods/main.py
pat2vec/tests/config_pat2vec.py
pat2vec/tests/test_calculate_interval.py
pat2vec/tests/test_config_class.py
pat2vec/tests/test_filter_dataframe_by_timestamp_extended.py
pat2vec/tests/test_generate_date_list.py
pat2vec/tests/test_get_dummy_data_cohort_searcher_get_date.py
pat2vec/tests/test_get_method_bloods.py
pat2vec-0.1.1.dist-info/METADATA
pat2vec-0.1.1.dist-info/WHEEL
pat2vec-0.1.1.dist-info/top_level.txt
pat2vec-0.1.1.dist-info/RECORD
