Metadata-Version: 2.4
Name: pat2vec
Version: 0.1.1
Summary: A comprehensive Python package for healthcare data engineering, designed to extract, transform, and feature engineer patient data from CogStack-based electronic health record (EHR) datalakes. It provides tools for cohort building, batch data processing, clinical note analysis, and creating machine learning-ready datasets.
Home-page: https://github.com/SamoraHunter/pat2vec.git
Author: Samora Hunter
Author-email: Samora Hunter <samorahunter@gmail.com>
Project-URL: Homepage, https://github.com/SamoraHunter/pat2vec
Project-URL: Documentation, https://samorahunter.github.io/pat2vec/
Project-URL: Repository, https://github.com/SamoraHunter/pat2vec
Project-URL: Changelog, https://github.com/SamoraHunter/pat2vec/releases
Classifier: Programming Language :: Python :: 3
Classifier: License :: OSI Approved :: MIT License
Classifier: Operating System :: OS Independent
Requires-Python: >=3.10
Requires-Dist: medcat==1.16.0
Requires-Dist: paramiko
Requires-Dist: colorama
Requires-Dist: elasticsearch==8.17.0
Requires-Dist: eland==8.17.0
Requires-Dist: faker
Requires-Dist: fuzzywuzzy
Requires-Dist: seaborn
Requires-Dist: rapidfuzz
Requires-Dist: python-pptx
Requires-Dist: ipykernel
Requires-Dist: transformers==4.48.1
Requires-Dist: accelerate==1.3.0
Requires-Dist: peft==0.8.2
Requires-Dist: huggingface-hub==0.27.1
Requires-Dist: polars
Requires-Dist: pandas>=1.5.3
Requires-Dist: numpy>=1.25.2
Provides-Extra: all
Requires-Dist: torch>=2.5.1; extra == "all"
Requires-Dist: scikit-learn>=1.6.1; extra == "all"
Requires-Dist: jupyterlab; extra == "all"
Requires-Dist: lifelines==0.28.0; extra == "all"
Requires-Dist: bokeh==3.6.2; extra == "all"
Requires-Dist: dask; extra == "all"
Requires-Dist: datasets; extra == "all"
Requires-Dist: numba; extra == "all"
Requires-Dist: statsmodels; extra == "all"
Requires-Dist: wordcloud; extra == "all"
Requires-Dist: matplotlib-venn; extra == "all"
Requires-Dist: nltk; extra == "all"
Requires-Dist: sqlalchemy; extra == "all"
Requires-Dist: openpyxl; extra == "all"
Requires-Dist: pydot; extra == "all"
Requires-Dist: pyodbc; extra == "all"
Requires-Dist: python-tds; extra == "all"
Requires-Dist: umls-api; extra == "all"
Provides-Extra: dev
Requires-Dist: pytest; extra == "dev"
Requires-Dist: nbformat; extra == "dev"
Requires-Dist: nbconvert; extra == "dev"
Requires-Dist: nbstripout; extra == "dev"
Requires-Dist: nbmake; extra == "dev"
Requires-Dist: pre-commit; extra == "dev"
Requires-Dist: sphinx==8.1.3; extra == "dev"
Requires-Dist: sphinx-rtd-theme==3.0.2; extra == "dev"
Requires-Dist: myst-parser==4.0.1; extra == "dev"
Requires-Dist: sphinx-autodoc-typehints==3.0.1; extra == "dev"
Requires-Dist: sphinxcontrib-mermaid; extra == "dev"
Dynamic: author
Dynamic: home-page
